ct_clock.py
ct_clock-0.5.0.dist-info/LICENSE
ct_clock-0.5.0.dist-info/METADATA
ct_clock-0.5.0.dist-info/WHEEL
ct_clock-0.5.0.dist-info/entry_points.txt
ct_clock-0.5.0.dist-info/top_level.txt
ct_clock-0.5.0.dist-info/RECORD
