Metadata-Version: 2.1
Name: ct-clock
Version: 0.5.0
Summary: curses terminal digital clock
Home-page: https://github.com/tech-chad/ct_clock
Author: Chad Larson
Author-email: techchad2@gmail.com
License: MIT
Platform: UNKNOWN
Classifier: Programming Language :: Python :: 3
Classifier: Programming Language :: Python :: 3.6
Classifier: Programming Language :: Python :: 3.7
Classifier: Programming Language :: Python :: 3.8
Requires-Python: >=3.6.1
License-File: LICENSE
Requires-Dist: time-machine (>=2.4.0)
